{"cameraMode":{"drawMode":0,"name":"Shaded","section":"Shading Mode"},"sceneLighting":true,"audioPlay":false,"sceneViewState":{"showFog":true,"showMaterialUpdate":false,"showSkybox":true,"showFlares":true,"showImageEffects":true,"showParticleSystems":true},"in2DMode":false,"pivot":{"x":360.1009216308594,"y":657.9395141601563,"z":-19.5068359375},"rotation":{"x":0.012307336553931237,"y":0.018307046964764596,"z":-0.00022948333935346454,"w":0.9997698068618774},"size":2089.142333984375,"orthographic":false}